{
  "timestamp": "2025-11-14T18:34:38.141Z",
  "baseUrl": "http://localhost:8080",
  "pages": {
    "list": {
      "url": "http://localhost:8080/crud6/groups",
      "requests": [
        {
          "url": "http://localhost:8080/api/crud6/groups/schema?context=list",
          "method": "GET",
          "type": "xhr",
          "status": 200,
          "statusText": "OK",
          "timestamp": "2025-11-14T18:34:40.234Z",
          "responseTime": "2025-11-14T18:34:40.715Z"
        },
        {
          "url": "http://localhost:8080/api/crud6/groups",
          "method": "GET",
          "type": "xhr",
          "status": 200,
          "statusText": "OK",
          "timestamp": "2025-11-14T18:34:40.720Z",
          "responseTime": "2025-11-14T18:34:40.965Z"
        }
      ]
    },
    "detail": {
      "url": "http://localhost:8080/crud6/groups/1",
      "requests": [
        {
          "url": "http://localhost:8080/api/crud6/groups/schema?context=detail",
          "method": "GET",
          "type": "xhr",
          "status": 200,
          "statusText": "OK",
          "timestamp": "2025-11-14T18:34:42.123Z",
          "responseTime": "2025-11-14T18:34:42.589Z"
        },
        {
          "url": "http://localhost:8080/api/crud6/groups/1",
          "method": "GET",
          "type": "xhr",
          "status": 200,
          "statusText": "OK",
          "timestamp": "2025-11-14T18:34:42.594Z",
          "responseTime": "2025-11-14T18:34:42.798Z"
        }
      ]
    }
  },
  "summary": {
    "totalRequests": 4,
    "listPageRequests": 2,
    "detailPageRequests": 2,
    "schemaApiCalls": {
      "list": 1,
      "detail": 1
    },
    "yamlImports": {
      "list": 0,
      "detail": 0
    }
  }
}
